{
      "posts" : 
      [
        {
          "id" : "1" ,   
          "context": "Считалось, что где-то за Чертановской боковые ответвления от основных туннелей ныряли вниз, вплетаясь в грандиозный лабиринт природных пещер, по слухам, кишевших всяческой нечистью. Это место на станции условно называли «Вратами» – условно, потому что никто из живых обитателей Севастопольской его никогда не видел. Правда, известен был случай, когда еще на заре освоения линии сами Врата вроде бы обнаружила большая разведгруппа, преодолевшая Чертановскую. Группа несла с собой передатчик – что-то наподобие проводного телефона. По этому телефону связист и сообщил на Севастопольскую, что разведчики стоят на входе в уходящий почти вертикально вниз неширокий коридор. Больше он ничего передать не успел, но еще несколько минут, пока не порвался кабель, сгрудившееся вокруг переговорного устройства командование Севастопольской слушало, как один за другим обрываются истошные, полные ужаса и нечеловеческой боли вопли бойцов разведгруппы. Стрелять никто из них даже не пытался, словно каждому из погибающих было ясно, что обычное оружие не в состоянии защитить их. Последним замолк командир группы, наемник-головорез с Китай-города, собиравший коллекцию мизинцев своих врагов. Он, видимо, находился на некотором расстоянии от уроненной радистом трубки, поэтому разобрать, что он говорил, было непросто; но, вслушавшись в его предсмертные всхлипывания, начальник станции узнал молитву – из простых, наивных, которым верующие родители учат маленьких детей.",
          "score": 0.6,
          "answer": {
             "first" : "10",
             "second" : "22"
            }
                    
        },
        {
          "id" : "2" ,   
          "context": "Считалось, что где-то за Чертановской боковые ответвления от основных туннелей ныряли вниз, вплетаясь в грандиозный лабиринт природных пещер, по слухам, кишевших всяческой нечистью. Это место на станции условно называли «Вратами» – условно, потому что никто из живых обитателей Севастопольской его никогда не видел. Правда, известен был случай, когда еще на заре освоения линии сами Врата вроде бы обнаружила большая разведгруппа, преодолевшая Чертановскую. Группа несла с собой передатчик – что-то наподобие проводного телефона. По этому телефону связист и сообщил на Севастопольскую, что разведчики стоят на входе в уходящий почти вертикально вниз неширокий коридор. Больше он ничего передать не успел, но еще несколько минут, пока не порвался кабель, сгрудившееся вокруг переговорного устройства командование Севастопольской слушало, как один за другим обрываются истошные, полные ужаса и нечеловеческой боли вопли бойцов разведгруппы. Стрелять никто из них даже не пытался, словно каждому из погибающих было ясно, что обычное оружие не в состоянии защитить их. Последним замолк командир группы, наемник-головорез с Китай-города, собиравший коллекцию мизинцев своих врагов. Он, видимо, находился на некотором расстоянии от уроненной радистом трубки, поэтому разобрать, что он говорил, было непросто; но, вслушавшись в его предсмертные всхлипывания, начальник станции узнал молитву – из простых, наивных, которым верующие родители учат маленьких детей.",
          "score": 0.7,
          "answer": {
             "first" : "0",
             "second" : "22"
            }
                    
        },
        {
          "id" : "3" ,   
          "context": "kjsdhohd kjcnx lckjv vllv xkjc cj jc",
          "score": 0.9,
          "answer": {
             "first" : 2,
             "second" : 6
            }
                    
        },
        {
          "context": "kjsdhohd kjcnx lckjv vllv xkjc cj jc ",
          "score": "0.6",
          "answer": "kjcnx lckjv"
        },
        {
          "context": "kjsdhohd kjcnx lckjv vllv xkjc cj jc ",
          "score": "0.6",
          "answer": "kjsdhohd kjcnx lckjv vllv"
        },
        {
          "context": "kjsdhohd kjcnx lckjv vllv xkjc cj jc ",
          "score": "0.6",
          "answer": "xkjc"
        },
        {
          "context": "kjsdhohd kjcnx lckjv vllv xkjc cj jc ",
          "score": "0.6",
          "answer": "lckjv vllv"
        },
        {
          "context": "kjsdhohd kjcnx lckjv vllv xkjc cj jc ",
          "score": "0.6",
          "answer": "lckjv vllv"
        },
        {
          "context": "kjsdhohd kjcnx lckjv vllv xkjc cj jc ",
          "score": "0.6",
          "answer": "kjcnx lckjv vllv"
        },
        {
          "context": "kjsdhohd kjcnx lckjv vllv xkjc cj jc ",
          "score": "0.6",
          "answer": "kjcnx lckjv vllv"
        },
        {
          "context": "kjsdhohd kjcnx lckjv vllv xkjc cj jc ",
          "score": "0.6",
          "answer": "kjcnx lckjv vllv"
        },
        {
          "context": "kjsdhohd kjcnx lckjv vllv xkjc cj jc ",
          "score": "0.6",
          "answer": "kjcnx lckjv vllv"
        }
      ]
}
